cmat2aset/__init__.py
cmat2aset/cmat2aset.pyc
cmat2aset/cmat2tset.py
cmat2aset/gen_aset.py
cmat2aset/gen_pset.py
cmat2aset/interpolate_pset.py
LICENSE
cmat2aset-0.1.0.dist-info/LICENSE
cmat2aset-0.1.0.dist-info/WHEEL
cmat2aset-0.1.0.dist-info/METADATA
cmat2aset-0.1.0.dist-info/RECORD
